CHANGES.txt
MANIFEST.in
README.txt
setup.py
src/rsl/__init__.py
src/rsl.xsd.egg-info/PKG-INFO
src/rsl.xsd.egg-info/SOURCES.txt
src/rsl.xsd.egg-info/dependency_links.txt
src/rsl.xsd.egg-info/entry_points.txt
src/rsl.xsd.egg-info/namespace_packages.txt
src/rsl.xsd.egg-info/requires.txt
src/rsl.xsd.egg-info/top_level.txt
src/rsl/xsd/__init__.py
src/rsl/xsd/component.py
src/rsl/xsd/deserialtypes.py
src/rsl/xsd/factories.py
src/rsl/xsd/interfaces.py
src/rsl/xsd/manager.py
src/rsl/xsd/namespace.py
src/rsl/xsd/schema.py
src/rsl/xsd/serializer.py
src/rsl/xsd/simpletype.py
src/rsl/xsd/urtype.py
src/rsl/xsd/xsds/xml.xsd